[
 {
  "label": "p258",
  "tau": 2.0,
  "F": 8.434364318077314e-13,
  "iters": 20,
  "one_mR2": 0.2450946694711909,
  "slope": 0.38314634842415346,
  "wall": 0.0
 },
 {
  "label": "p258",
  "tau": 1.99,
  "F": 3.7636560534792807e-13,
  "iters": 15,
  "one_mR2": 0.2454117772332086,
  "slope": 0.3833356564855354,
  "wall": 2.693806951000056
 },
 {
  "label": "p258",
  "tau": 1.98,
  "F": 7.877032359715486e-13,
  "iters": 15,
  "one_mR2": 0.24572736513340107,
  "slope": 0.383527860974336,
  "wall": 2.7297322250000207
 },
 {
  "label": "p258",
  "tau": 1.97,
  "F": 5.343503417520878e-13,
  "iters": 16,
  "one_mR2": 0.2460413902605378,
  "slope": 0.38372298519585046,
  "wall": 3.1047723390000783
 },
 {
  "label": "p258",
  "tau": 1.96,
  "F": 4.271027975732977e-13,
  "iters": 17,
  "one_mR2": 0.24635380996644804,
  "slope": 0.38392105193873205,
  "wall": 3.115845669999999
 },
 {
  "label": "p258",
  "tau": 1.95,
  "F": 4.4775294583132563e-13,
  "iters": 18,
  "one_mR2": 0.24666458173859612,
  "slope": 0.3841220835359035,
  "wall": 3.3151053490000777
 },
 {
  "label": "p258",
  "tau": 1.94,
  "F": 5.078160114635466e-13,
  "iters": 19,
  "one_mR2": NaN,
  "slope": NaN,
  "wall": 3.8793981970000004
 },
 {
  "label": "p258",
  "tau": 1.93,
  "F": 7.827072323607354e-13,
  "iters": 19,
  "one_mR2": NaN,
  "slope": NaN,
  "wall": 3.884509499000046
 },
 {
  "label": "p258",
  "tau": 1.92,
  "F": 7.938094626069869e-13,
  "iters": 20,
  "one_mR2": NaN,
  "slope": NaN,
  "wall": 3.974212298999987
 },
 {
  "label": "p258",
  "tau": 1.91,
  "F": 3.485767230415604e-12,
  "iters": 20,
  "one_mR2": NaN,
  "slope": NaN,
  "wall": 4.253673523999964
 },
 {
  "label": "p258",
  "tau": 1.9,
  "F": 4.378220008760536e-12,
  "iters": 20,
  "one_mR2": NaN,
  "slope": NaN,
  "wall": 4.136336477999976
 },
 {
  "label": "p258",
  "tau": 1.89,
  "F": 2.5672686199129657e-11,
  "iters": 20,
  "one_mR2": 0.24849224345276133,
  "slope": 0.38539171923036786,
  "wall": 4.012643514000047
 },
 {
  "label": "p258",
  "tau": 1.88,
  "F": 4.016076360358056e-11,
  "iters": 20,
  "one_mR2": NaN,
  "slope": NaN,
  "wall": 4.3588090719999855
 },
 {
  "label": "p258",
  "tau": 1.87,
  "F": 1.888048606346615e-10,
  "iters": 20,
  "one_mR2": NaN,
  "slope": NaN,
  "wall": 4.099140136000074
 },
 {
  "label": "p258",
  "tau": 1.86,
  "F": 1.1411793732207798e-09,
  "iters": 20,
  "one_mR2": NaN,
  "slope": NaN,
  "wall": 4.1257456060000095
 },
 {
  "label": "p258",
  "tau": 1.85,
  "F": 1.33827032788858e-09,
  "iters": 20,
  "one_mR2": NaN,
  "slope": NaN,
  "wall": 4.296825307999939
 },
 {
  "label": "p258",
  "tau": 1.84,
  "F": 9.814356549675551e-09,
  "iters": 20,
  "one_mR2": NaN,
  "slope": NaN,
  "wall": 4.212295862000019
 },
 {
  "label": "p258",
  "tau": 1.83,
  "F": 6.084535758565934e-08,
  "iters": 20,
  "one_mR2": NaN,
  "slope": NaN,
  "wall": 4.0960651599999665
 },
 {
  "label": "p258",
  "tau": 1.82,
  "F": 3.715800196424368e-07,
  "iters": 20,
  "one_mR2": NaN,
  "slope": NaN,
  "wall": 4.0850366829999984
 },
 {
  "label": "p258",
  "tau": 1.81,
  "F": 8.245897180070294e-07,
  "iters": 20,
  "one_mR2": NaN,
  "slope": NaN,
  "wall": 4.153028654999957
 },
 {
  "label": "p258",
  "tau": 1.8,
  "F": 1.000590941435675e-06,
  "iters": 20,
  "one_mR2": NaN,
  "slope": NaN,
  "wall": 4.109444754000037
 },
 {
  "label": "p258",
  "tau": 1.79,
  "F": 1.0890670290919502e-05,
  "iters": 20,
  "one_mR2": 0.25137441956925416,
  "slope": 0.38775897491022887,
  "wall": 4.308966349000002
 },
 {
  "label": "p258",
  "tau": 1.78,
  "F": 1.326050380612287e-12,
  "iters": 20,
  "one_mR2": NaN,
  "slope": NaN,
  "wall": 4.489051308999933
 },
 {
  "label": "p258",
  "tau": 1.77,
  "F": 9.052475435922247e-11,
  "iters": 20,
  "one_mR2": NaN,
  "slope": NaN,
  "wall": 4.710727441000017
 },
 {
  "label": "p258",
  "tau": 1.76,
  "F": 3.1345748219280267e-10,
  "iters": 20,
  "one_mR2": NaN,
  "slope": NaN,
  "wall": 4.907386131999942
 },
 {
  "label": "p258",
  "tau": 1.75,
  "F": 4.396878905410517e-08,
  "iters": 20,
  "one_mR2": NaN,
  "slope": NaN,
  "wall": 4.821425271999942
 },
 {
  "label": "p258",
  "tau": 1.74,
  "F": 1.0564952268588002e-07,
  "iters": 20,
  "one_mR2": NaN,
  "slope": NaN,
  "wall": 5.136279019999961
 },
 {
  "label": "p258",
  "tau": 1.73,
  "F": 2.6989988810566246e-07,
  "iters": 20,
  "one_mR2": NaN,
  "slope": NaN,
  "wall": 5.204749803000027
 },
 {
  "label": "p258",
  "tau": 1.72,
  "F": 4.3170706476303167e-07,
  "iters": 20,
  "one_mR2": NaN,
  "slope": NaN,
  "wall": 5.497994275999986
 },
 {
  "label": "p258",
  "tau": 1.71,
  "F": 1.796248866314798e-07,
  "iters": 20,
  "one_mR2": NaN,
  "slope": NaN,
  "wall": 5.575545963000081
 },
 {
  "label": "p258",
  "tau": 1.7,
  "F": 6.093568749587774e-07,
  "iters": 20,
  "one_mR2": NaN,
  "slope": NaN,
  "wall": 5.612534858999993
 },
 {
  "label": "p258",
  "tau": 1.69,
  "F": 6.218612961794712e-07,
  "iters": 20,
  "one_mR2": 0.2540308617258806,
  "slope": 0.39044783034433855,
  "wall": 5.873030533000019
 },
 {
  "label": "p258",
  "tau": 1.68,
  "F": 2.7422662393083996e-06,
  "iters": 9,
  "one_mR2": NaN,
  "slope": NaN,
  "wall": 3.55567970300001
 },
 {
  "label": "p258",
  "tau": 1.67,
  "F": 4.3549504795681315e-06,
  "iters": 9,
  "one_mR2": NaN,
  "slope": NaN,
  "wall": 3.745724203000009
 },
 {
  "label": "p258",
  "tau": 1.66,
  "F": 1.1522859695217713e-05,
  "iters": 20,
  "one_mR2": NaN,
  "slope": NaN,
  "wall": 7.070793373000015
 },
 {
  "label": "p258",
  "tau": 1.65,
  "F": 6.517681876427872e-06,
  "iters": 20,
  "one_mR2": NaN,
  "slope": NaN,
  "wall": 8.09561399100005
 },
 {
  "label": "p258",
  "tau": 1.64,
  "F": 0.00035436786013084975,
  "iters": 5,
  "one_mR2": NaN,
  "slope": NaN,
  "wall": 4.006316039000012
 },
 {
  "label": "p258",
  "tau": 1.63,
  "F": 0.0005560390820512628,
  "iters": 2,
  "one_mR2": NaN,
  "slope": NaN,
  "wall": 1.257673154000031
 },
 {
  "label": "p258",
  "tau": 1.62,
  "F": 0.0008115621944538853,
  "iters": 5,
  "one_mR2": NaN,
  "slope": NaN,
  "wall": 3.7494237849999763
 },
 {
  "label": "p258",
  "tau": 1.61,
  "F": 0.0010472945866140115,
  "iters": 3,
  "one_mR2": NaN,
  "slope": NaN,
  "wall": 2.061397720000059
 },
 {
  "label": "p258",
  "tau": 1.6,
  "F": 0.001260265681515993,
  "iters": 2,
  "one_mR2": NaN,
  "slope": NaN,
  "wall": 1.2445554380000203
 },
 {
  "label": "p258",
  "tau": 1.59,
  "F": 0.001453914818218327,
  "iters": 2,
  "one_mR2": NaN,
  "slope": NaN,
  "wall": 1.4058849609999697
 },
 {
  "label": "p258",
  "tau": 1.58,
  "F": 0.0016254659048250408,
  "iters": 2,
  "one_mR2": NaN,
  "slope": NaN,
  "wall": 1.2886118610000494
 },
 {
  "label": "p258",
  "tau": 1.57,
  "F": 0.0019904054408807492,
  "iters": 2,
  "one_mR2": NaN,
  "slope": NaN,
  "wall": 1.2141395460000695
 },
 {
  "label": "p258",
  "tau": 1.56,
  "F": 0.0019314990816829414,
  "iters": 1,
  "one_mR2": NaN,
  "slope": NaN,
  "wall": 0.9309394549999297
 },
 {
  "label": "p258",
  "tau": 1.55,
  "F": 0.0022043059565296508,
  "iters": 2,
  "one_mR2": NaN,
  "slope": NaN,
  "wall": 1.258351398000059
 },
 {
  "label": "p258",
  "tau": 1.54,
  "F": 0.002146222519888219,
  "iters": 1,
  "one_mR2": NaN,
  "slope": NaN,
  "wall": 1.000130014999968
 },
 {
  "label": "p258",
  "tau": 1.53,
  "F": 0.002338789951101261,
  "iters": 2,
  "one_mR2": NaN,
  "slope": NaN,
  "wall": 1.298240901999975
 },
 {
  "label": "p258",
  "tau": 1.52,
  "F": 0.0023150876263540177,
  "iters": 2,
  "one_mR2": NaN,
  "slope": NaN,
  "wall": 1.4580072379999365
 },
 {
  "label": "p258",
  "tau": 1.51,
  "F": 0.0024521099804665214,
  "iters": 2,
  "one_mR2": NaN,
  "slope": NaN,
  "wall": 1.229188659999977
 },
 {
  "label": "p258",
  "tau": 1.5,
  "F": 0.002409045455013803,
  "iters": 2,
  "one_mR2": NaN,
  "slope": NaN,
  "wall": 1.5550249460000032
 },
 {
  "label": "p258",
  "tau": 1.49,
  "F": 0.002763263522483239,
  "iters": 2,
  "one_mR2": NaN,
  "slope": NaN,
  "wall": 1.2072028410000257
 },
 {
  "label": "p258",
  "tau": 1.48,
  "F": 0.002562851598109095,
  "iters": 1,
  "one_mR2": NaN,
  "slope": NaN,
  "wall": 0.9532803969999577
 },
 {
  "label": "p258",
  "tau": 1.47,
  "F": 0.002508899978188206,
  "iters": 1,
  "one_mR2": NaN,
  "slope": NaN,
  "wall": 0.9617997919999652
 },
 {
  "label": "p258",
  "tau": 1.46,
  "F": 0.0025579861926124936,
  "iters": 2,
  "one_mR2": NaN,
  "slope": NaN,
  "wall": 1.254980240000009
 },
 {
  "label": "p258",
  "tau": 1.45,
  "F": 0.002505277465207678,
  "iters": 1,
  "one_mR2": NaN,
  "slope": NaN,
  "wall": 0.9783483520000118
 },
 {
  "label": "p258",
  "tau": 1.44,
  "F": 0.0027628529904083488,
  "iters": 2,
  "one_mR2": NaN,
  "slope": NaN,
  "wall": 1.2524754849999908
 },
 {
  "label": "p258",
  "tau": 1.43,
  "F": 0.0024810655571714246,
  "iters": 1,
  "one_mR2": NaN,
  "slope": NaN,
  "wall": 1.0182356660000096
 },
 {
  "label": "p258",
  "tau": 1.42,
  "F": 0.0024307770630661585,
  "iters": 1,
  "one_mR2": NaN,
  "slope": NaN,
  "wall": 0.9847327510000241
 },
 {
  "label": "p258",
  "tau": 1.41,
  "F": 0.0026937739405410444,
  "iters": 2,
  "one_mR2": NaN,
  "slope": NaN,
  "wall": 1.2211061680000057
 },
 {
  "label": "p258",
  "tau": 1.4,
  "F": 0.002364854943242456,
  "iters": 1,
  "one_mR2": NaN,
  "slope": NaN,
  "wall": 1.0001381240000455
 }
]