[
 {
  "label": "p357",
  "tau": 2.0,
  "F": 3.389510894180603e-13,
  "iters": 21,
  "one_mR2": 0.24580566196103049,
  "slope": 0.225131316005891,
  "wall": 0.0
 },
 {
  "label": "p357",
  "tau": 1.99,
  "F": 3.7664316110408436e-13,
  "iters": 15,
  "one_mR2": 0.24770263251830987,
  "slope": 0.22462642147366854,
  "wall": 3.3144806950000003
 },
 {
  "label": "p357",
  "tau": 1.98,
  "F": 7.88868970147405e-13,
  "iters": 15,
  "one_mR2": 0.24962265393667216,
  "slope": 0.2241158008368369,
  "wall": 3.2755772550000017
 },
 {
  "label": "p357",
  "tau": 1.97,
  "F": 5.330180741225377e-13,
  "iters": 16,
  "one_mR2": 0.2515660329493983,
  "slope": 0.22359933788104117,
  "wall": 3.440537387000006
 },
 {
  "label": "p357",
  "tau": 1.96,
  "F": 4.276579090856103e-13,
  "iters": 17,
  "one_mR2": 0.2535330790329163,
  "slope": 0.2230769201242736,
  "wall": 3.794116090000003
 },
 {
  "label": "p357",
  "tau": 1.95,
  "F": 4.4775294583132563e-13,
  "iters": 18,
  "one_mR2": 0.25552410431283545,
  "slope": 0.2225484379101541,
  "wall": 3.9560153040000046
 },
 {
  "label": "p357",
  "tau": 1.94,
  "F": 5.078160114635466e-13,
  "iters": 19,
  "one_mR2": NaN,
  "slope": NaN,
  "wall": 4.192550619999992
 },
 {
  "label": "p357",
  "tau": 1.93,
  "F": 7.827072323607354e-13,
  "iters": 19,
  "one_mR2": NaN,
  "slope": NaN,
  "wall": 4.378780077999977
 },
 {
  "label": "p357",
  "tau": 1.92,
  "F": 7.938094626069869e-13,
  "iters": 20,
  "one_mR2": NaN,
  "slope": NaN,
  "wall": 4.531016627999975
 },
 {
  "label": "p357",
  "tau": 1.91,
  "F": 3.4858782527180665e-12,
  "iters": 20,
  "one_mR2": NaN,
  "slope": NaN,
  "wall": 4.688157332999992
 },
 {
  "label": "p357",
  "tau": 1.9,
  "F": 4.376055073862517e-12,
  "iters": 20,
  "one_mR2": NaN,
  "slope": NaN,
  "wall": 4.747157391000002
 },
 {
  "label": "p357",
  "tau": 1.89,
  "F": 2.5671686998407495e-11,
  "iters": 20,
  "one_mR2": 0.26799160906447167,
  "slope": 0.21924426934764618,
  "wall": 4.78215575599998
 },
 {
  "label": "p357",
  "tau": 1.88,
  "F": 4.494510319474898e-11,
  "iters": 20,
  "one_mR2": NaN,
  "slope": NaN,
  "wall": 4.882480777000012
 },
 {
  "label": "p357",
  "tau": 1.87,
  "F": 1.8880336183357826e-10,
  "iters": 20,
  "one_mR2": NaN,
  "slope": NaN,
  "wall": 4.913599392999998
 },
 {
  "label": "p357",
  "tau": 1.86,
  "F": 1.1411430689278745e-09,
  "iters": 20,
  "one_mR2": NaN,
  "slope": NaN,
  "wall": 4.8023977500000115
 },
 {
  "label": "p357",
  "tau": 1.85,
  "F": 1.338272770379234e-09,
  "iters": 20,
  "one_mR2": NaN,
  "slope": NaN,
  "wall": 4.872762108000018
 },
 {
  "label": "p357",
  "tau": 1.84,
  "F": 9.814355661497132e-09,
  "iters": 20,
  "one_mR2": NaN,
  "slope": NaN,
  "wall": 4.947706323000006
 },
 {
  "label": "p357",
  "tau": 1.83,
  "F": 6.084535630890286e-08,
  "iters": 20,
  "one_mR2": NaN,
  "slope": NaN,
  "wall": 4.978022315000004
 },
 {
  "label": "p357",
  "tau": 1.82,
  "F": 3.7158001892079184e-07,
  "iters": 20,
  "one_mR2": NaN,
  "slope": NaN,
  "wall": 4.857745997000023
 },
 {
  "label": "p357",
  "tau": 1.81,
  "F": 8.245897130665369e-07,
  "iters": 20,
  "one_mR2": NaN,
  "slope": NaN,
  "wall": 4.943870967000009
 },
 {
  "label": "p357",
  "tau": 1.8,
  "F": 1.0005909464871898e-06,
  "iters": 20,
  "one_mR2": NaN,
  "slope": NaN,
  "wall": 4.875998267999989
 },
 {
  "label": "p357",
  "tau": 1.79,
  "F": 1.089067028647861e-05,
  "iters": 20,
  "one_mR2": 0.2908831654546921,
  "slope": 0.21318733934356537,
  "wall": 4.954618844999999
 },
 {
  "label": "p357",
  "tau": 1.78,
  "F": 1.3264389586709058e-12,
  "iters": 20,
  "one_mR2": NaN,
  "slope": NaN,
  "wall": 5.241291954000019
 },
 {
  "label": "p357",
  "tau": 1.77,
  "F": 9.052192329050968e-11,
  "iters": 20,
  "one_mR2": NaN,
  "slope": NaN,
  "wall": 5.560428295999998
 },
 {
  "label": "p357",
  "tau": 1.76,
  "F": 3.134514869884697e-10,
  "iters": 20,
  "one_mR2": NaN,
  "slope": NaN,
  "wall": 5.706119082000015
 },
 {
  "label": "p357",
  "tau": 1.75,
  "F": 4.396878672263682e-08,
  "iters": 20,
  "one_mR2": NaN,
  "slope": NaN,
  "wall": 5.858878771000008
 },
 {
  "label": "p357",
  "tau": 1.74,
  "F": 1.0564951624658647e-07,
  "iters": 20,
  "one_mR2": NaN,
  "slope": NaN,
  "wall": 6.319408805999984
 },
 {
  "label": "p357",
  "tau": 1.73,
  "F": 2.6989988949344124e-07,
  "iters": 20,
  "one_mR2": NaN,
  "slope": NaN,
  "wall": 6.361901204000048
 },
 {
  "label": "p357",
  "tau": 1.72,
  "F": 4.317070664283662e-07,
  "iters": 20,
  "one_mR2": NaN,
  "slope": NaN,
  "wall": 6.423601351000002
 },
 {
  "label": "p357",
  "tau": 1.71,
  "F": 1.796248872976136e-07,
  "iters": 20,
  "one_mR2": NaN,
  "slope": NaN,
  "wall": 6.842044386000055
 },
 {
  "label": "p357",
  "tau": 1.7,
  "F": 9.334732986587824e-11,
  "iters": 20,
  "one_mR2": NaN,
  "slope": NaN,
  "wall": 6.355907792999972
 },
 {
  "label": "p357",
  "tau": 1.69,
  "F": 6.267720310537683e-07,
  "iters": 20,
  "one_mR2": 0.3167766771462355,
  "slope": 0.20633869296518198,
  "wall": 6.865799579999987
 },
 {
  "label": "p357",
  "tau": 1.68,
  "F": 2.857710328374452e-07,
  "iters": 20,
  "one_mR2": NaN,
  "slope": NaN,
  "wall": 7.606762570000001
 },
 {
  "label": "p357",
  "tau": 1.67,
  "F": 6.120721793845263e-07,
  "iters": 20,
  "one_mR2": NaN,
  "slope": NaN,
  "wall": 8.147686007000004
 },
 {
  "label": "p357",
  "tau": 1.66,
  "F": 6.095147245421817e-06,
  "iters": 20,
  "one_mR2": NaN,
  "slope": NaN,
  "wall": 8.587679648999995
 },
 {
  "label": "p357",
  "tau": 1.65,
  "F": 3.4061932077111834e-06,
  "iters": 20,
  "one_mR2": NaN,
  "slope": NaN,
  "wall": 9.897466637000036
 },
 {
  "label": "p357",
  "tau": 1.64,
  "F": 0.0003184318377125184,
  "iters": 3,
  "one_mR2": NaN,
  "slope": NaN,
  "wall": 2.50373079000002
 },
 {
  "label": "p357",
  "tau": 1.63,
  "F": 0.0005504083950273186,
  "iters": 6,
  "one_mR2": NaN,
  "slope": NaN,
  "wall": 4.529950143999997
 },
 {
  "label": "p357",
  "tau": 1.62,
  "F": 0.0007700387209985671,
  "iters": 4,
  "one_mR2": NaN,
  "slope": NaN,
  "wall": 3.169976195000004
 },
 {
  "label": "p357",
  "tau": 1.61,
  "F": 0.0009730576733816276,
  "iters": 4,
  "one_mR2": NaN,
  "slope": NaN,
  "wall": 3.292175432000022
 },
 {
  "label": "p357",
  "tau": 1.6,
  "F": 0.0011536248740760258,
  "iters": 3,
  "one_mR2": NaN,
  "slope": NaN,
  "wall": 2.525364317000026
 }
]